pySPADS/__init__.py
pySPADS/cli.py
pySPADS/optimization/__init__.py
pySPADS/pipeline/__init__.py
pySPADS/pipeline/steps.py
pySPADS/processing/__init__.py
pySPADS/processing/bridge.py
pySPADS/processing/data.py
pySPADS/processing/dataclasses.py
pySPADS/processing/recomposition.py
pySPADS/processing/reconstruct.py
pySPADS/processing/significance.py
pySPADS/processing/trend.py
pySPADS/root/__init__.py
pySPADS/util/__init__.py
pySPADS/util/click.py
pySPADS/visualisation/__init__.py
pySPADS/visualisation/drivers.py
pySPADS/visualisation/imfs.py
pySPADS/visualisation/paper.py
pyspads-0.0.2.dist-info/entry_points.txt
pyspads-0.0.2.dist-info/WHEEL
pyspads-0.0.2.dist-info/METADATA
pyspads-0.0.2.dist-info/RECORD
